collective.tiles.carousel-1.1.2-py3.13-nspkg.pth
collective/tiles/carousel/__init__.py
collective/tiles/carousel/configure.zcml
collective/tiles/carousel/interfaces.py
collective/tiles/carousel/setuphandlers.py
collective/tiles/carousel/testing.py
collective/tiles/carousel/tile.pt
collective/tiles/carousel/tile.py
collective/tiles/carousel/utils.py
collective/tiles/carousel/locales/README.rst
collective/tiles/carousel/locales/__init__.py
collective/tiles/carousel/locales/collective.tiles.carousel.pot
collective/tiles/carousel/locales/update.py
collective/tiles/carousel/locales/update.sh
collective/tiles/carousel/locales/en/LC_MESSAGES/collective.tiles.carousel.mo
collective/tiles/carousel/locales/en/LC_MESSAGES/collective.tiles.carousel.po
collective/tiles/carousel/profiles/default/browserlayer.xml
collective/tiles/carousel/profiles/default/metadata.xml
collective/tiles/carousel/profiles/default/registry/mosaic.xml
collective/tiles/carousel/profiles/uninstall/browserlayer.xml
collective/tiles/carousel/slides/__init__.py
collective/tiles/carousel/slides/configure.zcml
collective/tiles/carousel/slides/slide_full_view.pt
collective/tiles/carousel/slides/slide_full_view.py
collective/tiles/carousel/slides/slide_view.pt
collective/tiles/carousel/slides/slide_view.py
collective/tiles/carousel/slides/static/.gitkeep
collective/tiles/carousel/tests/__init__.py
collective/tiles/carousel/tests/test_robot.py
collective/tiles/carousel/tests/test_setup.py
collective/tiles/carousel/tests/robot/test_example.robot
collective_tiles_carousel-1.1.2.dist-info/LICENSE.GPL
collective_tiles_carousel-1.1.2.dist-info/LICENSE.rst
collective_tiles_carousel-1.1.2.dist-info/METADATA
collective_tiles_carousel-1.1.2.dist-info/WHEEL
collective_tiles_carousel-1.1.2.dist-info/entry_points.txt
collective_tiles_carousel-1.1.2.dist-info/namespace_packages.txt
collective_tiles_carousel-1.1.2.dist-info/top_level.txt
collective_tiles_carousel-1.1.2.dist-info/RECORD
