Metadata-Version: 2.2
Name: collective.tiles.carousel
Version: 1.1.2
Summary: Slider for plone.app.mosaic based on Bootstrap 5
Home-page: https://github.com/collective/collective.tiles.carousel
Author: Peter Holzer
Author-email: peter.holzer@agitator.com
License: GPL version 2
Project-URL: PyPI, https://pypi.python.org/pypi/collective.tiles.carousel
Project-URL: Source, https://github.com/collective/collective.tiles.carousel
Project-URL: Tracker, https://github.com/collective/collective.tiles.carousel/issues
Keywords: Python Plone CMS
Classifier: Development Status :: 5 - Production/Stable
Classifier: Environment :: Web Environment
Classifier: Framework :: Plone
Classifier: Framework :: Plone :: Addon
Classifier: Framework :: Plone :: 6.0
Classifier: Programming Language :: Python
Classifier: Programming Language :: Python :: 3.8
Classifier: Programming Language :: Python :: 3.9
Classifier: Programming Language :: Python :: 3.10
Classifier: Programming Language :: Python :: 3.11
Classifier: Operating System :: OS Independent
Classifier: License :: OSI Approved :: GNU General Public License v2 (GPLv2)
Requires-Python: >=3.8
License-File: LICENSE.GPL
License-File: LICENSE.rst
Requires-Dist: setuptools
Requires-Dist: Products.GenericSetup
Requires-Dist: plone.app.contenttypes
Requires-Dist: plone.app.querystring
Requires-Dist: plone.app.mosaic
Requires-Dist: plone.app.tiles
Requires-Dist: plone.app.z3cform
Requires-Dist: plone.autoform
Requires-Dist: plone.base
Requires-Dist: plone.dexterity
Requires-Dist: plone.memoize
Requires-Dist: plone.supermodel
Requires-Dist: plone.tiles
Requires-Dist: plone.api
Requires-Dist: z3c.relationfield
Provides-Extra: test
Requires-Dist: plone.app.dexterity; extra == "test"
Requires-Dist: plone.app.testing; extra == "test"
Requires-Dist: plone.browserlayer; extra == "test"
Requires-Dist: plone.testing; extra == "test"
Requires-Dist: plone.app.robotframework[debug]; extra == "test"
Requires-Dist: robotsuite; extra == "test"
Dynamic: author
Dynamic: author-email
Dynamic: classifier
Dynamic: description
Dynamic: home-page
Dynamic: keywords
Dynamic: license
Dynamic: project-url
Dynamic: provides-extra
Dynamic: requires-dist
Dynamic: requires-python
Dynamic: summary
